geoprofile/__init__.py
geoprofile/_version.py
geoprofile/column.py
geoprofile/constant.py
geoprofile/profile.py
geoprofile-0.4.0.dist-info/licenses/LICENSE
geoprofile-0.4.0.dist-info/METADATA
geoprofile-0.4.0.dist-info/WHEEL
geoprofile-0.4.0.dist-info/top_level.txt
geoprofile-0.4.0.dist-info/RECORD
