Metadata-Version: 2.4
Name: GeoProfile
Version: 0.4.0
Summary: A Python library for visualizing geotechnical profiles.
Project-URL: repository, https://github.com/cemsbv/GeoProfile
Keywords: visualizing
Requires-Python: >=3.11
License-File: LICENSE
Requires-Dist: plotly<7,>=6.0.1
Requires-Dist: shapely<3,>=2.1.0
Requires-Dist: python-tsp<0.6,>=0.5.0
Requires-Dist: scikit-spatial<10,>=9.0.1
Requires-Dist: scipy<2,>=1.15.2
Requires-Dist: tqdm<5,>=4.67.1
Provides-Extra: map
Requires-Dist: geopandas<2,>=1.0.1; extra == "map"
Requires-Dist: contextily<2,>=1.6.2; extra == "map"
Requires-Dist: matplotlib<4,>=3.10.1; extra == "map"
Provides-Extra: plot
Requires-Dist: kaleido<2,>=1; extra == "plot"
Provides-Extra: gef
Requires-Dist: pygef<0.12,>=0.11.1; extra == "gef"
Provides-Extra: notebook
Requires-Dist: cems-nuclei[client]<4,>=3.0.0; extra == "notebook"
Provides-Extra: test
Requires-Dist: coveralls==3.3.1; extra == "test"
Requires-Dist: pytest<9,>=8.3.5; extra == "test"
Provides-Extra: docs
Requires-Dist: Sphinx==8.2.3; extra == "docs"
Requires-Dist: sphinx-autodoc-typehints==3.1.0; extra == "docs"
Requires-Dist: ipython==9.1.0; extra == "docs"
Requires-Dist: asteroid-sphinx-theme==0.0.3; extra == "docs"
Requires-Dist: sphinx_rtd_theme==3.0.2; extra == "docs"
Requires-Dist: m2r2<0.4,>=0.3.4; extra == "docs"
Dynamic: license-file
